sy_custom/XTI_hijack.py
sy_custom/__init__.py
sy_custom/fine_tune.py
sy_custom/flux_minimal_inference.py
sy_custom/flux_train.py
sy_custom/flux_train_network.py
sy_custom/gen_img.py
sy_custom/gen_img_diffusers.py
sy_custom/inference_test.py
sy_custom/inference_test2.py
sy_custom/sd3_minimal_inference.py
sy_custom/sd3_train.py
sy_custom/sd3_train_network.py
sy_custom/sdxl_gen_img.py
sy_custom/sdxl_minimal_inference.py
sy_custom/sdxl_train.py
sy_custom/sdxl_train_control_net.py
sy_custom/sdxl_train_control_net_lllite.py
sy_custom/sdxl_train_control_net_lllite_old.py
sy_custom/sdxl_train_network.py
sy_custom/sdxl_train_textual_inversion.py
sy_custom/setup.py
sy_custom/train_controlnet.py
sy_custom/train_db.py
sy_custom/train_network.py
sy_custom/train_textual_inversion.py
sy_custom/train_textual_inversion_XTI.py
sy_custom-0.0.1.dist-info/METADATA
sy_custom-0.0.1.dist-info/WHEEL
sy_custom-0.0.1.dist-info/top_level.txt
sy_custom-0.0.1.dist-info/RECORD
