Metadata-Version: 2.1
Name: sy_custom
Version: 0.0.1
Summary: utilities for AI models with Pytorch by SY
Home-page: https://github.com/dneirfi/sy_custom.git
Author: sy.noh
Author-email: nshinyeong@gmail.com
Keywords: sy_custom
Classifier: Programming Language :: Python :: 3.6
Classifier: Programming Language :: Python :: 3.7
Classifier: Programming Language :: Python :: 3.8
Classifier: Programming Language :: Python :: 3.9
Requires-Python: >=3.6
Requires-Dist: tqdm
Requires-Dist: pandas
Requires-Dist: scikit-learn
